stock_core/__init__.py
stock_core/db_settings.pickle
stock_core/load_db.py
stock_core/repairman.py
stock_core/dart/__init__.py
stock_core/dart/analysis.pickle
stock_core/dart/analysis.py
stock_core/dart/oldtemp.py
stock_core/dart/save_db.py
stock_core/dart/subjects.py
stock_core/miscrapy/__init__.py
stock_core/miscrapy/scraper.py
stock_core/miscrapy/scrapy.cfg
stock_core/miscrapy/mi/__init__.py
stock_core/miscrapy/mi/items.py
stock_core/miscrapy/mi/middlewares.py
stock_core/miscrapy/mi/pipelines.py
stock_core/miscrapy/mi/settings.py
stock_core/miscrapy/mi/sqlite_db.py
stock_core/miscrapy/mi/spiders/__init__.py
stock_core/miscrapy/mi/spiders/aud.py
stock_core/miscrapy/mi/spiders/chf.py
stock_core/miscrapy/mi/spiders/gbond3y.py
stock_core/miscrapy/mi/spiders/gold.py
stock_core/miscrapy/mi/spiders/kosdaq.py
stock_core/miscrapy/mi/spiders/kospi.py
stock_core/miscrapy/mi/spiders/mihistory.py
stock_core/miscrapy/mi/spiders/silver.py
stock_core/miscrapy/mi/spiders/sp500.py
stock_core/miscrapy/mi/spiders/usdidx.py
stock_core/miscrapy/mi/spiders/usdkrw.py
stock_core/miscrapy/mi/spiders/wti.py
stock_core/nfscrapy/__init__.py
stock_core/nfscrapy/scraper.py
stock_core/nfscrapy/scrapy.cfg
stock_core/nfscrapy/nfs/__init__.py
stock_core/nfscrapy/nfs/items.py
stock_core/nfscrapy/nfs/middlewares.py
stock_core/nfscrapy/nfs/pipelines.py
stock_core/nfscrapy/nfs/settings.py
stock_core/nfscrapy/nfs/sqlite_db.py
stock_core/nfscrapy/nfs/spiders/__init__.py
stock_core/nfscrapy/nfs/spiders/c101.py
stock_core/nfscrapy/nfs/spiders/c103.py
stock_core/nfscrapy/nfs/spiders/c104.py
stock_core/nfscrapy/nfs/spiders/c106.py
stock_core/nfscrapy/nfs/spiders/c108.py
stock_core/nfscrapy/nfs/spiders/common.py
stock_core-0.4.6.dist-info/LICENSE
stock_core-0.4.6.dist-info/METADATA
stock_core-0.4.6.dist-info/WHEEL
stock_core-0.4.6.dist-info/top_level.txt
stock_core-0.4.6.dist-info/RECORD
