Metadata-Version: 2.1
Name: stock-core
Version: 0.4.6
Summary: The cores of my stock program
Home-page: https://pypi.org/project/stock_core/
Author: hyungjin kim
Author-email: hj3415@gmail.com
License: UNKNOWN
Project-URL: Bug Tracker, https://pypi.org/project/stock_core/
Platform: UNKNOWN
Classifier: Programming Language :: Python :: 3
Classifier: License :: OSI Approved :: MIT License
Classifier: Operating System :: OS Independent
Requires-Python: >=3.6
License-File: LICENSE
Requires-Dist: scrapy (>=2.5.0)
Requires-Dist: pandas (>=1.2.4)
Requires-Dist: selenium (>=3.141.0)
Requires-Dist: webdriver-manager (>=3.4.0)
Requires-Dist: pymongo (>=3.11.4)
Requires-Dist: sqlalchemy (>=1.4.14)
Requires-Dist: requests (>=2.25.1)
Requires-Dist: beautifulsoup4 (>=4.9.3)
Requires-Dist: html5lib (>=1.1)
Requires-Dist: krx-hj3415 (>=0.2.6)
Requires-Dist: util-hj3415 (>=0.2.0)
Requires-Dist: eval-hj3415 (>=0.1.7)
